{"anger": {"score": 0, "percentage": 0.0, "words": [], "count": {}}, "anticipation": {"score": 8, "percentage": 0.047337278106508875, "words": ["top", "shopping", "top", "top", "top", "vacation", "vacation", "top"], "count": {"top": 5, "shopping": 1, "vacation": 2}}, "disgust": {"score": 0, "percentage": 0.0, "words": [], "count": {}}, "fear": {"score": 0, "percentage": 0.0, "words": [], "count": {}}, "joy": {"score": 5, "percentage": 0.029585798816568046, "words": ["save", "save", "shopping", "vacation", "vacation"], "count": {"save": 2, "shopping": 1, "vacation": 2}}, "negative": {"score": 4, "percentage": 0.023668639053254437, "words": ["rift", "zip", "zip", "zip"], "count": {"rift": 1, "zip": 3}}, "positive": {"score": 15, "percentage": 0.08875739644970414, "words": ["save", "top", "save", "shopping", "top", "customer", "prime", "top", "top", "professional", "render", "vacation", "vacation", "qualified", "top"], "count": {"save": 2, "top": 5, "shopping": 1, "customer": 1, "prime": 1, "professional": 1, "render": 1, "vacation": 2, "qualified": 1}}, "sadness": {"score": 0, "percentage": 0.0, "words": [], "count": {}}, "surprise": {"score": 1, "percentage": 0.005917159763313609, "words": ["shopping"], "count": {"shopping": 1}}, "trust": {"score": 10, "percentage": 0.05917159763313609, "words": ["save", "top", "save", "shopping", "top", "top", "top", "professional", "qualified", "top"], "count": {"save": 2, "top": 5, "shopping": 1, "professional": 1, "qualified": 1}}}